README
setup.py
src/django_skypehub.egg-info/PKG-INFO
src/django_skypehub.egg-info/SOURCES.txt
src/django_skypehub.egg-info/dependency_links.txt
src/django_skypehub.egg-info/not-zip-safe
src/django_skypehub.egg-info/requires.txt
src/django_skypehub.egg-info/top_level.txt
src/skypehub/__init__.py
src/skypehub/admin.py
src/skypehub/decorators.py
src/skypehub/forms.py
src/skypehub/handlers.py
src/skypehub/models.py
src/skypehub/test.py
src/skypehub/urls.py
src/skypehub/utils.py
src/skypehub/views.py
src/skypehub/management/__init__.py
src/skypehub/management/commands/__init__.py
src/skypehub/management/commands/runskypebot.py