Metadata-Version: 1.1
Name: django-skypehub
Version: 0.3.0
Summary: Skype API bridge for Django
Home-page: http://bitbucket.org/tokibito/django-skypehub/
Author: Shinya Okano
Author-email: tokibito@gmail.com
License: BSD
Keywords: django skype
Platform: UNKNOWN
Classifier: Development Status :: 3 - Alpha
Classifier: Environment :: Web Environment
Classifier: Framework :: Django
Classifier: License :: OSI Approved :: BSD License
Classifier: Programming Language :: Python
